banana_straightener/__init__.py
banana_straightener/agent.py
banana_straightener/cli.py
banana_straightener/config.py
banana_straightener/models.py
banana_straightener/ui.py
banana_straightener/utils.py
banana_straightener-0.2.1.dist-info/licenses/LICENSE
banana_straightener-0.2.1.dist-info/METADATA
banana_straightener-0.2.1.dist-info/WHEEL
banana_straightener-0.2.1.dist-info/entry_points.txt
banana_straightener-0.2.1.dist-info/top_level.txt
banana_straightener-0.2.1.dist-info/RECORD
