Metadata-Version: 2.4
Name: banana-straightener
Version: 0.2.1
Summary: Self-correcting image generation using Gemini - iterate until it's right!
Home-page: https://github.com/velvet-shark/banana-straightener
Author: Radek Sienkiewicz
Author-email: Radek Sienkiewicz <mail@velvetshark.com>
Project-URL: Homepage, https://github.com/velvet-shark/banana-straightener
Project-URL: Bug Reports, https://github.com/velvet-shark/banana-straightener/issues
Project-URL: Source, https://github.com/velvet-shark/banana-straightener
Classifier: Development Status :: 3 - Alpha
Classifier: Intended Audience :: Developers
Classifier: Topic :: Software Development :: Libraries :: Python Modules
Classifier: License :: OSI Approved :: MIT License
Classifier: Programming Language :: Python :: 3
Classifier: Programming Language :: Python :: 3.10
Classifier: Programming Language :: Python :: 3.11
Classifier: Programming Language :: Python :: 3.12
Requires-Python: >=3.10
License-File: LICENSE
Requires-Dist: Pillow>=10.0.0
Requires-Dist: click>=8.0.0
Requires-Dist: gradio>=5.0.0
Requires-Dist: python-dotenv>=1.0.0
Requires-Dist: rich>=13.0.0
Requires-Dist: pydantic>=2.0.0
Requires-Dist: tenacity>=8.0.0
Requires-Dist: google-genai
Provides-Extra: dev
Requires-Dist: pytest>=7.0.0; extra == "dev"
Requires-Dist: pytest-cov>=4.0.0; extra == "dev"
Requires-Dist: black>=23.0.0; extra == "dev"
Requires-Dist: flake8>=6.0.0; extra == "dev"
Requires-Dist: mypy>=1.0.0; extra == "dev"
Dynamic: author
Dynamic: home-page
Dynamic: license-file
Dynamic: requires-python
